bbftools/core/__init__.py
bbftools/core/pyproject.py
bbftools/core/sphinx.py
bbftools-0.1.1.dist-info/LICENSE
bbftools-0.1.1.dist-info/METADATA
bbftools-0.1.1.dist-info/WHEEL
bbftools-0.1.1.dist-info/entry_points.txt
bbftools-0.1.1.dist-info/top_level.txt
bbftools-0.1.1.dist-info/RECORD
