Metadata-Version: 2.1
Name: bbftools
Version: 0.1.1
Summary: BBF Tools
Author-email: Broadband Forum <tools@broadband-forum.org>
Project-URL: Homepage, https://github.com/BroadbandForum/bbftools
Project-URL: Bug Tracker, https://github.com/BroadbandForum/bbftools/issues
Classifier: License :: OSI Approved :: BSD License
Classifier: Operating System :: OS Independent
Classifier: Programming Language :: Python :: 3
Requires-Python: >=3.9
License-File: LICENSE
Requires-Dist: build
Requires-Dist: furo
Requires-Dist: myst-parser
Requires-Dist: sphinx
Requires-Dist: sphinx-argparse
Requires-Dist: tomli
Requires-Dist: twine
